core/__init__.py
core/eao_optimizer.py
core/gqft_engine.py
core/mqb_compiler.py
core/validation.py
hmai-1.0.0.dist-info/METADATA
hmai-1.0.0.dist-info/WHEEL
hmai-1.0.0.dist-info/entry_points.txt
hmai-1.0.0.dist-info/top_level.txt
hmai-1.0.0.dist-info/RECORD
