Metadata-Version: 2.4
Name: hmai
Version: 1.0.0
Summary: AI framework for inventing new classes of matter through generative quantum field theory
Home-page: https://github.com/hmai/framework
Author: Krishna Bajpai, Vedanshi Gupta
Author-email: krishn@krishnabajpai.me, vedanshigupta18@gmail.com
Project-URL: Bug Tracker, https://github.com/hmai/framework/issues
Project-URL: Documentation, https://hmai.dev/docs
Project-URL: Source Code, https://github.com/hmai/framework
Project-URL: Homepage, https://hmai.dev
Keywords: materials science,quantum field theory,artificial intelligence,machine learning,physics simulation,materials discovery,exotic matter,metamaterials,quantum materials,computational physics
Classifier: Development Status :: 4 - Beta
Classifier: Intended Audience :: Science/Research
Classifier: Intended Audience :: Developers
Classifier: Topic :: Scientific/Engineering :: Physics
Classifier: Topic :: Scientific/Engineering :: Chemistry
Classifier: Topic :: Scientific/Engineering :: Artificial Intelligence
Classifier: License :: Other/Proprietary License
Classifier: Programming Language :: Python :: 3
Classifier: Programming Language :: Python :: 3.8
Classifier: Programming Language :: Python :: 3.9
Classifier: Programming Language :: Python :: 3.10
Classifier: Programming Language :: Python :: 3.11
Classifier: Operating System :: OS Independent
Requires-Python: >=3.8
Requires-Dist: tensorflow>=2.8.0
Requires-Dist: numpy>=1.21.0
Requires-Dist: scipy>=1.7.0
Requires-Dist: matplotlib>=3.5.0
Requires-Dist: pyyaml>=6.0
Requires-Dist: tqdm>=4.62.0
Requires-Dist: h5py>=3.6.0
Requires-Dist: scikit-learn>=1.1.0
Provides-Extra: dev
Requires-Dist: pytest>=7.0.0; extra == "dev"
Requires-Dist: pytest-cov>=3.0.0; extra == "dev"
Requires-Dist: black>=22.0.0; extra == "dev"
Requires-Dist: flake8>=4.0.0; extra == "dev"
Requires-Dist: mypy>=0.950; extra == "dev"
Provides-Extra: docs
Requires-Dist: mkdocs>=1.4.0; extra == "docs"
Requires-Dist: mkdocs-material>=8.0.0; extra == "docs"
Requires-Dist: mkdocs-material-extensions>=1.0.0; extra == "docs"
Provides-Extra: quantum
Requires-Dist: qiskit>=0.39.0; extra == "quantum"
Requires-Dist: cirq>=0.15.0; extra == "quantum"
Provides-Extra: viz
Requires-Dist: plotly>=5.0.0; extra == "viz"
Requires-Dist: bokeh>=2.4.0; extra == "viz"
Requires-Dist: mayavi; extra == "viz"
Dynamic: author
Dynamic: author-email
Dynamic: classifier
Dynamic: description
Dynamic: description-content-type
Dynamic: home-page
Dynamic: keywords
Dynamic: project-url
Dynamic: provides-extra
Dynamic: requires-dist
Dynamic: requires-python
Dynamic: summary
